barriersampling/__init__.py
barriersampling/barriersampler.py
barriersampling-0.0.2.dist-info/LICENSE
barriersampling-0.0.2.dist-info/METADATA
barriersampling-0.0.2.dist-info/WHEEL
barriersampling-0.0.2.dist-info/top_level.txt
barriersampling-0.0.2.dist-info/RECORD
