Metadata-Version: 2.2
Name: barriersampling
Version: 0.0.2
Summary: Implementation of Nested Sampling with Barriers
Author-email: Farin Lippmann <toucanmeister@gmail.com>
License: MIT
Project-URL: Homepage, https://github.com/toucanmeister/barriersampling
Keywords: python,statistics,sampling,bayes,optimization
Classifier: Programming Language :: Python :: 3
Classifier: Operating System :: OS Independent
Requires-Python: >=3.8
License-File: LICENSE
Requires-Dist: numpy
Requires-Dist: jax
Requires-Dist: matplotlib
Requires-Dist: scipy
